aiz/__init__.py
aiz/hmtai.py
hmtaipy/__init__.py
hmtaipy/hmtai.py
hmtaipy-1.0.0.data/scripts/hmtaipy.py
hmtaipy-1.0.0.data/scripts/py_hmtai
py_hmtai/__init__.py
py_hmtai/hmtai.py
pyhmtai/__init__.py
hmtaipy-1.0.0.dist-info/LICENSE
hmtaipy-1.0.0.dist-info/METADATA
hmtaipy-1.0.0.dist-info/WHEEL
hmtaipy-1.0.0.dist-info/top_level.txt
hmtaipy-1.0.0.dist-info/RECORD
