Metadata-Version: 2.1
Name: hmtaipy
Version: 1.0.0
Summary: API Wrapper of hmtai
Home-page: UNKNOWN
Author: TheCuteOwl
License: MIT
Platform: UNKNOWN
Classifier: Programming Language :: Python :: 3.10
Classifier: License :: OSI Approved :: MIT License
Classifier: Operating System :: OS Independent
Requires-Python: >=3.6
License-File: LICENSE
Requires-Dist: requests
